cfile/__init__.py
cfile/core.py
cfile/factory.py
cfile/style.py
cfile/writer.py
cfile-0.4.0.dist-info/LICENSE
cfile-0.4.0.dist-info/METADATA
cfile-0.4.0.dist-info/WHEEL
cfile-0.4.0.dist-info/top_level.txt
cfile-0.4.0.dist-info/RECORD
