Metadata-Version: 2.1
Name: cfile
Version: 0.4.0
Summary: A C code generator written in Python 3
Project-URL: Homepage, https://github.com/cogu/cfile
Project-URL: Issues, https://github.com/cogu/cfile/issues
Requires-Python: >=3.10
License-File: LICENSE
